honyx/__init__.py
honyx/utils.py
honyx/algorithms/__init__.py
honyx/algorithms/centrality.py
honyx/algorithms/predictions.py
honyx/algorithms/round_trips.py
honyx/models/__init__.py
honyx/models/fix_order_model.py
honyx/models/hon_model.py
honyx/models/optimal_order_model.py
honyx/models/saebi_von_model.py
honyx/models/sampling_von_model.py
honyx-0.1.1.dist-info/LICENSE
honyx-0.1.1.dist-info/METADATA
honyx-0.1.1.dist-info/WHEEL
honyx-0.1.1.dist-info/top_level.txt
honyx-0.1.1.dist-info/RECORD
