Metadata-Version: 2.1
Name: honyx
Version: 0.1.1
Summary: Python package for creating and analyzing Higher-order networks from sequential dataset
Author-email: Julie Queiros <julie.queiros@univ-nantes.fr>, Simon Artus <simon.artus@etu.univ-nantes.fr>, François Queyroi <francois.queyroi@univ-nantes.fr>
Project-URL: Homepage, https://gitlab.univ-nantes.fr/queyroi-f/honyx
Project-URL: Bug Tracker, https://gitlab.univ-nantes.fr/queyroi-f/honyx/-/issues
Project-URL: Source Code, https://gitlab.univ-nantes.fr/queyroi-f/honyx
Keywords: Networks,Graph Theory,Mathematics,network,graph,discrete mathematics,math
Platform: Linux
Platform: Mac OSX
Platform: Windows
Platform: Unix
Classifier: Programming Language :: Python :: 3
Classifier: License :: OSI Approved :: MIT License
Classifier: Operating System :: OS Independent
Requires-Python: >=3.8
License-File: LICENSE
Requires-Dist: networkx >=2.8
Requires-Dist: numpy >=1.22
Requires-Dist: scipy !=1.11.0,!=1.11.1,>=1.9
Provides-Extra: doc
Requires-Dist: sphinx >=7 ; extra == 'doc'
Requires-Dist: pydata-sphinx-theme >=0.13 ; extra == 'doc'
Requires-Dist: sphinx-gallery >=0.14 ; extra == 'doc'
Requires-Dist: numpydoc >=1.6 ; extra == 'doc'
